pypowerview/__init__.py
pypowerview-0.2.dist-info/LICENSE
pypowerview-0.2.dist-info/METADATA
pypowerview-0.2.dist-info/WHEEL
pypowerview-0.2.dist-info/top_level.txt
pypowerview-0.2.dist-info/RECORD
