Metadata-Version: 2.1
Name: pypowerview
Version: 0.2
Summary: Python API for talking to Powerview Hub
Home-page: https://github.com/koolsb/pypowerview
Author: Ben Kools
Author-email: koolsb@my.uwstout.edu
License: UNKNOWN
Platform: UNKNOWN
Classifier: Programming Language :: Python :: 3.6
Classifier: License :: OSI Approved :: MIT License
Classifier: Operating System :: OS Independent
Classifier: Development Status :: 4 - Beta
